README.txt
setup.cfg
setup.py
docs/HISTORY.txt
docs/INSTALL.txt
docs/LICENSE.GPL
docs/LICENSE.txt
experimental/__init__.py
experimental.aggressiveopaquespeedup.egg-info/PKG-INFO
experimental.aggressiveopaquespeedup.egg-info/SOURCES.txt
experimental.aggressiveopaquespeedup.egg-info/dependency_links.txt
experimental.aggressiveopaquespeedup.egg-info/entry_points.txt
experimental.aggressiveopaquespeedup.egg-info/namespace_packages.txt
experimental.aggressiveopaquespeedup.egg-info/not-zip-safe
experimental.aggressiveopaquespeedup.egg-info/requires.txt
experimental.aggressiveopaquespeedup.egg-info/top_level.txt
experimental/aggressiveopaquespeedup/__init__.py
experimental/aggressiveopaquespeedup/configure.zcml
experimental/aggressiveopaquespeedup/opaque.py