Metadata-Version: 1.0
Name: experimental.aggressiveopaquespeedup
Version: 1.1
Summary: A more aggressive opaquespeedup package to improve performance
Home-page: http://svn.plone.org/svn/collective/experimental.aggressiveopaquespeedup
Author: JeanMichel FRANCOIS aka toutpt
Author-email: makina-corpus.com
License: GPL
Platform: UNKNOWN
Classifier: Framework :: Plone
Classifier: Programming Language :: Python
Classifier: Topic :: Software Development :: Libraries :: Python Modules
